{
  "version-3.4/docs": [
    {
      "type": "category",
      "label": "Overview",
      "items": [
        {
          "type": "doc",
          "id": "version-3.4/installation"
        },
        {
          "type": "doc",
          "id": "version-3.4/defining-entities"
        },
        {
          "type": "doc",
          "id": "version-3.4/relationships"
        },
        {
          "type": "doc",
          "id": "version-3.4/entity-manager"
        },
        {
          "type": "doc",
          "id": "version-3.4/repositories"
        }
      ]
    },
    {
      "type": "category",
      "label": "Fundamentals",
      "items": [
        {
          "type": "doc",
          "id": "version-3.4/identity-map"
        },
        {
          "type": "doc",
          "id": "version-3.4/entity-references"
        },
        {
          "type": "doc",
          "id": "version-3.4/entity-constructors"
        },
        {
          "type": "doc",
          "id": "version-3.4/collections"
        },
        {
          "type": "doc",
          "id": "version-3.4/unit-of-work"
        },
        {
          "type": "doc",
          "id": "version-3.4/transactions"
        },
        {
          "type": "doc",
          "id": "version-3.4/cascading"
        },
        {
          "type": "doc",
          "id": "version-3.4/deployment"
        },
        {
          "type": "doc",
          "id": "version-3.4/decorators"
        }
      ]
    },
    {
      "type": "category",
      "label": "Advanced Features",
      "items": [
        {
          "type": "doc",
          "id": "version-3.4/nested-populate"
        },
        {
          "type": "doc",
          "id": "version-3.4/query-conditions"
        },
        {
          "type": "doc",
          "id": "version-3.4/query-builder"
        },
        {
          "type": "doc",
          "id": "version-3.4/propagation"
        },
        {
          "type": "doc",
          "id": "version-3.4/serializing"
        },
        {
          "type": "doc",
          "id": "version-3.4/entity-helper"
        },
        {
          "type": "doc",
          "id": "version-3.4/property-validation"
        },
        {
          "type": "doc",
          "id": "version-3.4/lifecycle-hooks"
        },
        {
          "type": "doc",
          "id": "version-3.4/naming-strategy"
        },
        {
          "type": "doc",
          "id": "version-3.4/custom-types"
        },
        {
          "type": "doc",
          "id": "version-3.4/entity-schema"
        },
        {
          "type": "doc",
          "id": "version-3.4/metadata-providers"
        },
        {
          "type": "doc",
          "id": "version-3.4/metadata-cache"
        },
        {
          "type": "doc",
          "id": "version-3.4/debugging"
        },
        {
          "type": "doc",
          "id": "version-3.4/schema-generator"
        },
        {
          "type": "doc",
          "id": "version-3.4/entity-generator"
        },
        {
          "type": "doc",
          "id": "version-3.4/migrations"
        },
        {
          "type": "doc",
          "id": "version-3.4/read-connections"
        },
        {
          "type": "doc",
          "id": "version-3.4/configuration"
        }
      ]
    },
    {
      "type": "category",
      "label": "Usage with Different Drivers",
      "items": [
        {
          "type": "doc",
          "id": "version-3.4/usage-with-sql"
        },
        {
          "type": "doc",
          "id": "version-3.4/usage-with-mongo"
        }
      ]
    },
    {
      "type": "category",
      "label": "Recipes",
      "items": [
        {
          "type": "doc",
          "id": "version-3.4/usage-with-nestjs"
        },
        {
          "type": "doc",
          "id": "version-3.4/usage-with-js"
        },
        {
          "type": "doc",
          "id": "version-3.4/custom-driver"
        },
        {
          "type": "doc",
          "id": "version-3.4/multiple-schemas"
        },
        {
          "type": "doc",
          "id": "version-3.4/using-bigint-pks"
        }
      ]
    },
    {
      "type": "category",
      "label": "Example Integrations",
      "items": [
        {
          "type": "link",
          "label": "Express + MongoDB + TypeScript",
          "href": "https://github.com/mikro-orm/express-ts-example-app"
        },
        {
          "type": "link",
          "label": "NestJS + MySQL + TypeScript",
          "href": "https://github.com/mikro-orm/nestjs-example-app"
        },
        {
          "type": "link",
          "label": "RealWorld example app (Nest + MySQL)",
          "href": "https://github.com/mikro-orm/nestjs-realworld-example-app"
        },
        {
          "type": "link",
          "label": "Express + MongoDB + JavaScript",
          "href": "https://github.com/mikro-orm/express-js-example-app"
        }
      ]
    }
  ]
}
